byted_tool_mayday/__init__.py
byted_tool_mayday-0.0.1.dist-info/METADATA
byted_tool_mayday-0.0.1.dist-info/WHEEL
byted_tool_mayday-0.0.1.dist-info/top_level.txt
byted_tool_mayday-0.0.1.dist-info/RECORD
